volvoDB/DB.py
volvoDB/DBConnection.py
volvoDB/__init__.py
VOLVO_DB-0.0.1.dist-info/LICENSE
VOLVO_DB-0.0.1.dist-info/METADATA
VOLVO_DB-0.0.1.dist-info/WHEEL
VOLVO_DB-0.0.1.dist-info/top_level.txt
VOLVO_DB-0.0.1.dist-info/RECORD
