Metadata-Version: 2.1
Name: VOLVO_DB
Version: 0.0.1
Summary: کتابخونه دیتابیس
Author-email: ابوالفضل میرزائی <mirzaiabolfazl6@gmail.com>
Classifier: Programming Language :: Python :: 3
Classifier: License :: OSI Approved :: MIT License
Classifier: Operating System :: OS Independent
Requires-Python: >=3.8
License-File: LICENSE
